recsys/__init__.py
recsys/__main__.py
recsys/pipeline_registry.py
recsys/settings.py
recsys/pipelines/__init__.py
recsys/pipelines/data_el/__init__.py
recsys/pipelines/data_el/nodes.py
recsys/pipelines/data_el/pipeline.py
recsys/pipelines/data_processing/__init__.py
recsys/pipelines/data_processing/nodes.py
recsys/pipelines/data_processing/pipeline.py
recsys/pipelines/ml_models/__init__.py
recsys/pipelines/ml_models/nodes.py
recsys/pipelines/ml_models/pipeline.py
recsys_wizos-0.1.3.dist-info/METADATA
recsys_wizos-0.1.3.dist-info/WHEEL
recsys_wizos-0.1.3.dist-info/entry_points.txt
recsys_wizos-0.1.3.dist-info/top_level.txt
recsys_wizos-0.1.3.dist-info/RECORD
