Metadata-Version: 2.4
Name: recsys-wizos
Version: 0.1.3
Requires-Python: >=3.9
Requires-Dist: ipython>=8.10
Requires-Dist: jupyterlab>=3.0
Requires-Dist: notebook
Requires-Dist: kedro[jupyter]~=0.19.10
Requires-Dist: kedro-datasets[matplotlib-matplotlibwriter,pandas-csvdataset,pandas-exceldataset,pandas-parquetdataset,plotly-jsondataset,plotly-plotlydataset]>=3.0
Requires-Dist: kedro-viz>=6.7.0
Requires-Dist: scikit-learn~=1.5.1
Requires-Dist: seaborn~=0.12.1
Requires-Dist: spacy~=3.8
Requires-Dist: mlxtend~=0.23
Requires-Dist: pyodbc~=5.2.0
Requires-Dist: adlfs==2024.12.0
Requires-Dist: pyarrow~=19.0
Provides-Extra: docs
Requires-Dist: docutils<0.21; extra == "docs"
Requires-Dist: sphinx<7.3,>=5.3; extra == "docs"
Requires-Dist: sphinx_rtd_theme==2.0.0; extra == "docs"
Requires-Dist: nbsphinx==0.8.1; extra == "docs"
Requires-Dist: sphinx-autodoc-typehints==1.20.2; extra == "docs"
Requires-Dist: sphinx_copybutton==0.5.2; extra == "docs"
Requires-Dist: ipykernel<7.0,>=5.3; extra == "docs"
Requires-Dist: Jinja2<3.2.0; extra == "docs"
Requires-Dist: myst-parser<2.1,>=1.0; extra == "docs"
Provides-Extra: dev
Requires-Dist: pytest-cov~=3.0; extra == "dev"
Requires-Dist: pytest-mock<2.0,>=1.7.1; extra == "dev"
Requires-Dist: pytest~=7.2; extra == "dev"
Requires-Dist: ruff~=0.8.0; extra == "dev"
Requires-Dist: nbstripout~=0.8.1; extra == "dev"
Provides-Extra: app
Requires-Dist: fastapi[standard]; extra == "app"
Requires-Dist: pydantic-settings>=2.0.0; extra == "app"
